{
    "_links": {
        "self": {
            "href": "http:\/\/drupal-business-and-community-days.de\/taxonomy\/term\/8?_format=hal_json"
        },
        "type": {
            "href": "http:\/\/drupal.org\/rest\/type\/taxonomy_term\/sponsor_level"
        }
    },
    "uuid": [
        {
            "value": "a59a9f83-d793-40c3-a501-1d49c25d7003"
        }
    ],
    "vid": [
        {
            "target_id": "sponsor_level"
        }
    ],
    "langcode": [
        {
            "value": "en",
            "lang": "en"
        }
    ],
    "name": [
        {
            "value": "Rasberry"
        }
    ],
    "weight": [
        {
            "value": "5"
        }
    ],
    "changed": [
        {
            "value": "1451419527"
        }
    ],
    "default_langcode": [
        {
            "value": "1",
            "lang": "en"
        }
    ]
}