{
    "_links": {
        "self": {
            "href": "http:\/\/drupal-business-and-community-days.de\/sites\/default\/files\/location-1.PNG"
        },
        "type": {
            "href": "http:\/\/drupal.org\/rest\/type\/file\/file"
        },
        "http:\/\/drupal.org\/rest\/relation\/file\/file\/uid": [
            {
                "href": "http:\/\/drupal-business-and-community-days.de\/user\/1?_format=hal_json"
            }
        ]
    },
    "uuid": [
        {
            "value": "5828cbc4-8090-464a-b909-9e9bb5ca8e5a"
        }
    ],
    "langcode": [
        {
            "value": "en"
        }
    ],
    "_embedded": {
        "http:\/\/drupal.org\/rest\/relation\/file\/file\/uid": [
            {
                "_links": {
                    "self": {
                        "href": "http:\/\/drupal-business-and-community-days.de\/user\/1?_format=hal_json"
                    },
                    "type": {
                        "href": "http:\/\/drupal.org\/rest\/type\/user\/user"
                    }
                },
                "uuid": [
                    {
                        "value": "881c0857-9f87-46a4-aa04-4d6698940e9b"
                    }
                ]
            }
        ]
    },
    "filename": [
        {
            "value": "location-1.PNG"
        }
    ],
    "uri": [
        {
            "value": "http:\/\/drupal-business-and-community-days.de\/sites\/default\/files\/location-1.PNG"
        }
    ],
    "filemime": [
        {
            "value": "image\/png"
        }
    ],
    "filesize": [
        {
            "value": "266681"
        }
    ],
    "status": [
        {
            "value": "1"
        }
    ],
    "created": [
        {
            "value": "1451476363"
        }
    ],
    "changed": [
        {
            "value": "1451476579"
        }
    ]
}
